thors_hammer/__init__.py
thors_hammer/main.py
thors_hammer-2.0.0.dist-info/LICENSE
thors_hammer-2.0.0.dist-info/METADATA
thors_hammer-2.0.0.dist-info/WHEEL
thors_hammer-2.0.0.dist-info/entry_points.txt
thors_hammer-2.0.0.dist-info/top_level.txt
thors_hammer-2.0.0.dist-info/RECORD
